batch-perceptron/__init__.py
batch-perceptron/main.py
batch_perceptron/__init__.py
batch_perceptron/main.py
batch_perceptron-0.1.4.dist-info/METADATA
batch_perceptron-0.1.4.dist-info/WHEEL
batch_perceptron-0.1.4.dist-info/entry_points.txt
batch_perceptron-0.1.4.dist-info/top_level.txt
batch_perceptron-0.1.4.dist-info/RECORD
